AB/__init__.py
AB/Rockwell/Types.py
AB/Rockwell/__init__.py
AB/Rockwell/XML/Tools.py
AB/Rockwell/XML/__init__.py
AB/Rockwell/XML/Templates/Base_Template.py
AB/Rockwell/XML/Templates/Controller.py
AB/Rockwell/XML/Templates/Datatype.py
AB/Rockwell/XML/Templates/Member.py
AB/Rockwell/XML/Templates/Program.py
AB/Rockwell/XML/Templates/Project.py
AB/Rockwell/XML/Templates/Routine.py
AB/Rockwell/XML/Templates/Rung.py
AB/Rockwell/XML/Templates/Tag.py
AB/Rockwell/XML/Templates/TagComment.py
AB/Rockwell/XML/Templates/__init__.py
allen_bradley_toolkit-2.0.1.dist-info/DESCRIPTION.rst
allen_bradley_toolkit-2.0.1.dist-info/METADATA
allen_bradley_toolkit-2.0.1.dist-info/RECORD
allen_bradley_toolkit-2.0.1.dist-info/WHEEL
allen_bradley_toolkit-2.0.1.dist-info/metadata.json
allen_bradley_toolkit-2.0.1.dist-info/top_level.txt
