Metadata-Version: 2.0
Name: allen-bradley-toolkit
Version: 2.0.1
Summary: Allen-Bradley Python Toolkit
Home-page: https://cmseaton42.github.io/Allen-Bradley-Toolkit/
Author: Canaan Seaton
Author-email: cmseaton42@gmail.com
License: MIT
Keywords: PLC Tools XML L5X LXML Rockwell Allen Bradley Allen-Bradley Python Python27
Platform: UNKNOWN
Classifier: Development Status :: 3 - Alpha
Classifier: Intended Audience :: Developers
Classifier: Topic :: Software Development :: Build Tools
Classifier: License :: OSI Approved :: MIT License
Classifier: Programming Language :: Python :: 2.7
Requires-Dist: lxml (>=3.6.0)
